poetry_demo/__init__.py
liyedong_poetry_demo-0.1.0.dist-info/METADATA
liyedong_poetry_demo-0.1.0.dist-info/WHEEL
liyedong_poetry_demo-0.1.0.dist-info/RECORD
