Metadata-Version: 2.1
Name: liyedong-poetry-demo
Version: 0.1.0
Summary: 
Author: liyedong
Author-email: lyd1446034545@gmail.com
Requires-Python: >=3.12,<4.0
Classifier: Programming Language :: Python :: 3
Classifier: Programming Language :: Python :: 3.12
Requires-Dist: apscheduler (>=3.10.4,<4.0.0)
Requires-Dist: drissionpage (>=4.1.0.7,<5.0.0.0)
Requires-Dist: pypiwin32 (>=223,<224)
Requires-Dist: requests (>=2.32.3,<3.0.0)
